deep_talk/__init__.py
deep_talk/down.py
deep_talk/qpro.pro
deep_talk/qpro.py
deep_talk/query.py
deep_talk-0.1.4.dist-info/LICENSE
deep_talk-0.1.4.dist-info/METADATA
deep_talk-0.1.4.dist-info/WHEEL
deep_talk-0.1.4.dist-info/top_level.txt
deep_talk-0.1.4.dist-info/RECORD
