Metadata-Version: 2.1
Name: deep-talk
Version: 0.1.4
Summary: DeepTalk: Python and Prolog based dialogue agent
Home-page: https://github.com/ptarau/DeepTalk.git
Author: Paul Tarau, Andrea Cortis
License: Apache
Platform: UNKNOWN
Requires-Dist: pyswip
Requires-Dist: graphviz
Requires-Dist: textcrafts
